PyInquirer/__init__.py
PyInquirer/color_print.py
PyInquirer/prompt.py
PyInquirer/prompts/__init__.py
PyInquirer/prompts/checkbox.py
PyInquirer/prompts/common.py
PyInquirer/prompts/confirm.py
PyInquirer/prompts/editor.py
PyInquirer/prompts/expand.py
PyInquirer/prompts/input.py
PyInquirer/prompts/list.py
PyInquirer/prompts/password.py
PyInquirer/prompts/rawlist.py
PyInquirer/separator.py
PyInquirer/utils.py
py_inquirer_cli-0.0.2.dist-info/LICENSE
py_inquirer_cli-0.0.2.dist-info/METADATA
py_inquirer_cli-0.0.2.dist-info/WHEEL
py_inquirer_cli-0.0.2.dist-info/RECORD
