Metadata-Version: 2.1
Name: py-inquirer-cli
Version: 0.0.2
Summary: A Python module for collection of common interactive command line user interfaces, based on Inquirer.js
License: MIT
Author: Oyetoke Toby
Author-email: oyetoketoby80@gmail.com
Requires-Python: >=3.8,<3.13
Classifier: License :: OSI Approved :: MIT License
Classifier: Programming Language :: Python :: 3
Classifier: Programming Language :: Python :: 3.8
Classifier: Programming Language :: Python :: 3.9
Classifier: Programming Language :: Python :: 3.10
Classifier: Programming Language :: Python :: 3.11
Classifier: Programming Language :: Python :: 3.12
Requires-Dist: prompt-toolkit (>=3.0.41,<4.0.0)
Requires-Dist: pygments (>=2.17.2,<3.0.0)
